awslogs_watch/__init__.py
awslogs_watch/_version.py
awslogs_watch/base.py
awslogs_watch/console.py
awslogs_watch/exceptions.py
awslogs_watch/model.py
awslogs_watch/lib/__init__.py
awslogs_watch/lib/execute.py
awslogs_watch/lib/path.py
awslogs_watch/lib/profile_config.py
awslogs_watch/lib/prompt.py
awslogs_watch-0.2.1.dist-info/LICENSE
awslogs_watch-0.2.1.dist-info/METADATA
awslogs_watch-0.2.1.dist-info/WHEEL
awslogs_watch-0.2.1.dist-info/entry_points.txt
awslogs_watch-0.2.1.dist-info/top_level.txt
awslogs_watch-0.2.1.dist-info/RECORD
