Metadata-Version: 2.1
Name: awslogs-watch
Version: 0.2.1
Summary: awslogs-watch is a CLI tool that makes it easy to use awslogs
Home-page: https://github.com/deresmos/awslogs-watch
Author: deresmos
Author-email: deresmos@gmail.com
License: MIT License
Keywords: tools
Platform: UNKNOWN
Requires-Python: >=3.6
Requires-Dist: prompt-toolkit (==2.0.9)
Requires-Dist: awslogs
Provides-Extra: develop
Requires-Dist: pytest ; extra == 'develop'
Requires-Dist: pytest-sugar ; extra == 'develop'
Requires-Dist: pytest-mock ; extra == 'develop'
Requires-Dist: black ; extra == 'develop'
